README.rst
setup.py
inspected.egg-info/PKG-INFO
inspected.egg-info/SOURCES.txt
inspected.egg-info/dependency_links.txt
inspected.egg-info/entry_points.txt
inspected.egg-info/requires.txt
inspected.egg-info/top_level.txt
inspector/__init__.py
inspector/annotators.py
inspector/describe.py
inspector/filters.py
inspector/utils.py