Metadata-Version: 1.1
Name: inspected
Version: 0.2.0
Summary: Reads your code and returns a JSON description you can use to generate documentation. Like Sphinx AutoDoc but without Sphinx.
Home-page: UNKNOWN
Author: Stijn Debrouwere
Author-email: stijn@debrouwere.org
License: ISC
Download-URL: http://www.github.com/debrouwere/python-inspector/tarball/master
Keywords: documentation inspect inspection introspection autodoc sphinx
Platform: UNKNOWN
Classifier: Development Status :: 4 - Beta
Classifier: Intended Audience :: Developers
Classifier: License :: OSI Approved :: MIT License
Classifier: Operating System :: OS Independent
Classifier: Programming Language :: Python
Classifier: Topic :: Utilities
